WaLSAtools/WaLSAtools.py
WaLSAtools/__init__.py
WaLSAtools/analysis_modules/WaLSA_confidence.py
WaLSAtools/analysis_modules/WaLSA_cross_spectra.py
WaLSAtools/analysis_modules/WaLSA_detrend_apod.py
WaLSAtools/analysis_modules/WaLSA_interactive.py
WaLSAtools/analysis_modules/WaLSA_io.py
WaLSAtools/analysis_modules/WaLSA_k_omega.py
WaLSAtools/analysis_modules/WaLSA_plot_k_omega.py
WaLSAtools/analysis_modules/WaLSA_plot_wavelet_spectrum.py
WaLSAtools/analysis_modules/WaLSA_pod.py
WaLSAtools/analysis_modules/WaLSA_speclizer.py
WaLSAtools/analysis_modules/WaLSA_wavelet.py
WaLSAtools/analysis_modules/WaLSA_wavelet_confidence.py
WaLSAtools/analysis_modules/__init__.py
WaLSAtools/analysis_modules/parameter_definitions.py
WaLSAtools/analysis_modules/PyEMD/BEMD.py
WaLSAtools/analysis_modules/PyEMD/CEEMDAN.py
WaLSAtools/analysis_modules/PyEMD/EEMD.py
WaLSAtools/analysis_modules/PyEMD/EMD.py
WaLSAtools/analysis_modules/PyEMD/EMD2d.py
WaLSAtools/analysis_modules/PyEMD/EMD_matlab.py
WaLSAtools/analysis_modules/PyEMD/__init__.py
WaLSAtools/analysis_modules/PyEMD/checks.py
WaLSAtools/analysis_modules/PyEMD/compact.py
WaLSAtools/analysis_modules/PyEMD/splines.py
WaLSAtools/analysis_modules/PyEMD/utils.py
WaLSAtools/analysis_modules/PyEMD/visualisation.py
WaLSAtools/analysis_modules/PyEMD/experimental/__init__.py
WaLSAtools/analysis_modules/PyEMD/experimental/jitemd.py
WaLSAtools/assets/WaLSA_logo.png
WaLSAtools/assets/WaLSAtools_black.png
walsatools-1.0.0.post5.dist-info/METADATA
walsatools-1.0.0.post5.dist-info/WHEEL
walsatools-1.0.0.post5.dist-info/entry_points.txt
walsatools-1.0.0.post5.dist-info/top_level.txt
walsatools-1.0.0.post5.dist-info/RECORD
