Metadata-Version: 2.4
Name: WaLSAtools
Version: 1.0.0.post5
Summary: Wave analysis tools: A package for analyzing wave and oscillatory signals
Home-page: https://github.com/WaLSAteam/WaLSAtools
Author: WaLSA Team - Shahin Jafarzadeh
Author-email: Shahin.Jafarzadeh@WaLSA.team
Classifier: Programming Language :: Python :: 3
Classifier: Intended Audience :: Science/Research
Classifier: License :: OSI Approved :: Apache Software License
Classifier: Operating System :: OS Independent
Requires-Python: >=3.6
Requires-Dist: astropy==7.0.1
Requires-Dist: ipython==8.32.0
Requires-Dist: ipywidgets==8.1.5
Requires-Dist: matplotlib==3.10.0
Requires-Dist: numba==0.61.0
Requires-Dist: numpy==2.1.3
Requires-Dist: pyFFTW==0.15.0
Requires-Dist: scipy==1.15.1
Requires-Dist: setuptools>=78.1.1
Requires-Dist: scikit-image==0.25.1
Requires-Dist: tqdm==4.67.1
Dynamic: author
Dynamic: author-email
Dynamic: classifier
Dynamic: description
Dynamic: description-content-type
Dynamic: home-page
Dynamic: requires-dist
Dynamic: requires-python
Dynamic: summary
